ak_sm_recorder/__init__.py
ak_sm_recorder/__main__.py
ak_sm_recorder/ak_sm_recorder/conf/gui_ka_single_mode.conf
ak_sm_recorder/ak_sm_recorder/conf/kinect_azure_settings.conf
camera_classes/KA_manager2.py
camera_classes/__init__.py
camera_classes/job_thread_3d_azure.py
camera_classes/job_thread_azure.py
camera_classes/test/__init__.py
camera_classes/test/test_job_thread_3D_azure.py
camera_classes/test/test_job_thread_azure.py
camera_classes/test/test_suite_camera_classes.py
gui_single_mode/__init__.py
gui_single_mode/about_window.py
gui_single_mode/gui_ak_single_config.py
gui_single_mode/gui_classes.py
gui_single_mode/assets/icon_app.png
gui_single_mode/assets/logo_grap.png
helpers/__init__.py
helpers/helper_filesystem.py
helpers/helper_load_config.py
helpers/helper_path.py
helpers/helpers_image.py
ak_sm_recorder-1.2.1.dist-info/LICENSE
ak_sm_recorder-1.2.1.dist-info/METADATA
ak_sm_recorder-1.2.1.dist-info/WHEEL
ak_sm_recorder-1.2.1.dist-info/top_level.txt
ak_sm_recorder-1.2.1.dist-info/RECORD
