Metadata-Version: 2.1
Name: ak-sm-recorder
Version: 1.2.1
Summary: A simple GUI recorder based on Python to manage Azure Kinect camera devices in a standalone mode.
Home-page: https://github.com/GRAP-UdL-AT/ak_sm_recorder
Author: Juan Carlos Miranda, Jordi Gene-Mola, Jaume Arno, Eduard Gregorio
Author-email: juancarlos.miranda@udl.cat, jordi.genemola@udl.cat, jaume.arno@udl.cat, eduard.gregorio@udl.cat
Project-URL: Bug Tracker, https://github.com/GRAP-UdL-AT/ak_sm_recorder/issues
Classifier: Programming Language :: Python :: 3
Classifier: License :: OSI Approved :: MIT License
Classifier: Operating System :: OS Independent
Requires-Python: >=3.8
License-File: LICENSE
Requires-Dist: certifi ==2022.12.7
Requires-Dist: charset-normalizer ==3.0.1
Requires-Dist: DateTime ==4.4
Requires-Dist: idna ==3.3
Requires-Dist: numpy ==1.24.2
Requires-Dist: opencv-python ==4.7.0.68
Requires-Dist: path ==16.6.0
Requires-Dist: pyk4a ==1.5.0
Requires-Dist: python-version ==0.0.2
Requires-Dist: pytz ==2022.7.1
Requires-Dist: requests ==2.28.2
Requires-Dist: urllib3 ==1.26.14
Requires-Dist: zope.interface ==5.4.0
